{
    "key": "group_62d0ee30cd3a2",
    "title": "Order Fields Page",
    "fields": [
        {
            "key": "field_62d0eea2d1c3c",
            "label": "Packages",
            "name": "packages",
            "type": "repeater",
            "instructions": "",
            "required": 0,
            "conditional_logic": 0,
            "wrapper": {
                "width": "",
                "class": "",
                "id": ""
            },
            "collapsed": "",
            "min": 0,
            "max": 0,
            "layout": "row",
            "button_label": "",
            "sub_fields": [
                {
                    "key": "field_62d0f60cfdb23",
                    "label": "Package Title",
                    "name": "package_title",
                    "type": "text",
                    "instructions": "",
                    "required": 0,
                    "conditional_logic": 0,
                    "wrapper": {
                        "width": "",
                        "class": "",
                        "id": ""
                    },
                    "default_value": "",
                    "placeholder": "",
                    "prepend": "",
                    "append": "",
                    "maxlength": ""
                },
                {
                    "key": "field_62d0f614fdb24",
                    "label": "Package Description",
                    "name": "package_description",
                    "type": "wysiwyg",
                    "instructions": "",
                    "required": 0,
                    "conditional_logic": 0,
                    "wrapper": {
                        "width": "",
                        "class": "",
                        "id": ""
                    },
                    "default_value": "",
                    "tabs": "all",
                    "toolbar": "full",
                    "media_upload": 1,
                    "delay": 0
                },
                {
                    "key": "field_62d0f628fdb25",
                    "label": "Package Product ID",
                    "name": "package_product_id",
                    "type": "post_object",
                    "instructions": "",
                    "required": 0,
                    "conditional_logic": 0,
                    "wrapper": {
                        "width": "",
                        "class": "",
                        "id": ""
                    },
                    "post_type": [
                        "product"
                    ],
                    "taxonomy": "",
                    "allow_null": 0,
                    "multiple": 0,
                    "return_format": "object",
                    "ui": 1
                }
            ]
        }
    ],
    "location": [
        [
            {
                "param": "page",
                "operator": "==",
                "value": "147"
            }
        ]
    ],
    "menu_order": 0,
    "position": "acf_after_title",
    "style": "default",
    "label_placement": "top",
    "instruction_placement": "label",
    "hide_on_screen": "",
    "active": true,
    "description": "",
    "show_in_rest": 0,
    "modified": 1657861724
}